onegov.onboarding-0.4.7-py3.6-nspkg.pth
onegov/onboarding/.gitignore
onegov/onboarding/__init__.py
onegov/onboarding/app.py
onegov/onboarding/errors.py
onegov/onboarding/layout.py
onegov/onboarding/path.py
onegov/onboarding/upgrade.py
onegov/onboarding/assets/js/awesomeplete.js
onegov/onboarding/assets/js/colorpicker.js
onegov/onboarding/assets/js/common.js
onegov/onboarding/assets/js/foundation.js
onegov/onboarding/assets/js/jquery.js
onegov/onboarding/assets/js/modernizr.js
onegov/onboarding/assets/js/placeholder.js
onegov/onboarding/assets/js/underscore.js
onegov/onboarding/forms/__init__.py
onegov/onboarding/forms/town.py
onegov/onboarding/locale/de_CH/LC_MESSAGES/onegov.onboarding.po
onegov/onboarding/models/__init__.py
onegov/onboarding/models/assistant.py
onegov/onboarding/models/town_assistant.py
onegov/onboarding/static/towns.json
onegov/onboarding/static/font-awesome/css/font-awesome.css
onegov/onboarding/static/font-awesome/css/font-awesome.min.css
onegov/onboarding/static/font-awesome/fonts/FontAwesome.otf
onegov/onboarding/static/font-awesome/fonts/fontawesome-webfont.eot
onegov/onboarding/static/font-awesome/fonts/fontawesome-webfont.svg
onegov/onboarding/static/font-awesome/fonts/fontawesome-webfont.ttf
onegov/onboarding/static/font-awesome/fonts/fontawesome-webfont.woff
onegov/onboarding/static/font-awesome/fonts/fontawesome-webfont.woff2
onegov/onboarding/static/font-awesome/less/animated.less
onegov/onboarding/static/font-awesome/less/bordered-pulled.less
onegov/onboarding/static/font-awesome/less/core.less
onegov/onboarding/static/font-awesome/less/fixed-width.less
onegov/onboarding/static/font-awesome/less/font-awesome.less
onegov/onboarding/static/font-awesome/less/icons.less
onegov/onboarding/static/font-awesome/less/larger.less
onegov/onboarding/static/font-awesome/less/list.less
onegov/onboarding/static/font-awesome/less/mixins.less
onegov/onboarding/static/font-awesome/less/path.less
onegov.onboarding-0.4.7.dist-info/METADATA
onegov.onboarding-0.4.7.dist-info/WHEEL
onegov.onboarding-0.4.7.dist-info/entry_points.txt
onegov.onboarding-0.4.7.dist-info/namespace_packages.txt
onegov.onboarding-0.4.7.dist-info/top_level.txt
onegov.onboarding-0.4.7.dist-info/RECORD
