Metadata-Version: 2.1
Name: onegov.onboarding
Version: 0.4.7
Summary: Onboarding for OneGov Cloud applications.
Home-page: http://github.com/OneGov/onegov.onboarding
Author: Seantis GmbH
Author-email: info@seantis.ch
License: GPLv2
Platform: any
Classifier: Intended Audience :: Developers
Classifier: Programming Language :: Python :: 3 :: Only
Classifier: Programming Language :: Python :: 3.6
Classifier: Programming Language :: Python :: 3.7
Classifier: Topic :: Software Development :: Libraries :: Python Modules
Classifier: License :: OSI Approved :: GNU General Public License v2 (GPLv2)
Requires-Python: >=3.6
Requires-Dist: cached-property
Requires-Dist: onegov.core (>=0.41.0)
Requires-Dist: onegov.foundation
Requires-Dist: onegov.org (>=0.11.0)
Requires-Dist: onegov.reservation
Requires-Dist: onegov.search
Requires-Dist: onegov.town (>=1.12.3)
Provides-Extra: test
Requires-Dist: coverage ; extra == 'test'
Requires-Dist: onegov-testing ; extra == 'test'
Requires-Dist: pytest ; extra == 'test'
Requires-Dist: pytest-localserver ; extra == 'test'
Requires-Dist: pyquery ; extra == 'test'
Requires-Dist: webtest ; extra == 'test'
